study_reminders_ACIT4420/__init__.py
study_reminders_ACIT4420/logger.py
study_reminders_ACIT4420/main.py
study_reminders_ACIT4420/reminder_generator.py
study_reminders_ACIT4420/reminder_log.txt
study_reminders_ACIT4420/reminder_sender.py
study_reminders_ACIT4420/scheduler.py
study_reminders_ACIT4420/students.json
study_reminders_ACIT4420/students_manager.py
study_reminders_acit4420-1.0.2.dist-info/METADATA
study_reminders_acit4420-1.0.2.dist-info/WHEEL
study_reminders_acit4420-1.0.2.dist-info/licenses/LICENSE
study_reminders_acit4420-1.0.2.dist-info/RECORD
