Metadata-Version: 2.4
Name: study_reminders_ACIT4420
Version: 1.0.2
Summary: For a school assignment, a Python package that automates the generation and distribution of personalized study reminders for students.
Author-email: M S <NotARealEmail@DontEmail.no>
License-Expression: MIT
License-File: LICENSE
Classifier: Operating System :: OS Independent
Classifier: Programming Language :: Python :: 3
Requires-Python: >=3.13
Requires-Dist: schedule
